ioiocore/__init__.py
ioiocore/__version__.py
ioiocore/configuration.py
ioiocore/constants.py
ioiocore/context.py
ioiocore/i_node.py
ioiocore/i_port.py
ioiocore/interface.py
ioiocore/io_node.py
ioiocore/logging.py
ioiocore/node.py
ioiocore/o_node.py
ioiocore/o_port.py
ioiocore/pipeline.py
ioiocore/port.py
ioiocore/portable.py
ioiocore/utilities.py
ioiocore/imp/__init__.py
ioiocore/imp/constants_imp.cp311-win_amd64.pyd
ioiocore/imp/i_node_imp.cp311-win_amd64.pyd
ioiocore/imp/i_port_imp.cp311-win_amd64.pyd
ioiocore/imp/implementation.cp311-win_amd64.pyd
ioiocore/imp/io_node_imp.cp311-win_amd64.pyd
ioiocore/imp/logging_imp.cp311-win_amd64.pyd
ioiocore/imp/node_imp.cp311-win_amd64.pyd
ioiocore/imp/o_node_imp.cp311-win_amd64.pyd
ioiocore/imp/o_port_imp.cp311-win_amd64.pyd
ioiocore/imp/pipeline_imp.cp311-win_amd64.pyd
ioiocore/imp/port_imp.cp311-win_amd64.pyd
ioiocore/imp/portable_imp.cp311-win_amd64.pyd
ioiocore-4.0.6.dist-info/licenses/LICENSE
ioiocore-4.0.6.dist-info/METADATA
ioiocore-4.0.6.dist-info/WHEEL
ioiocore-4.0.6.dist-info/top_level.txt
ioiocore-4.0.6.dist-info/RECORD
