Metadata-Version: 2.4
Name: ioiocore
Version: 4.0.6
Summary: A real-time signal processing framework for Python
Home-page: https://www.gtec.at
Author: g.tec medical engineering GmbH
Author-email: support@gtec.at
License: g.tec Non-Commercial License (GNCL)
Classifier: Development Status :: 4 - Beta
Classifier: Operating System :: OS Independent
Classifier: Programming Language :: Python :: 3
License-File: LICENSE
Dynamic: author
Dynamic: author-email
Dynamic: classifier
Dynamic: description
Dynamic: description-content-type
Dynamic: home-page
Dynamic: license
Dynamic: license-file
Dynamic: summary
